rpc_over_redis/core.py
rpc_over_redis/rpc_types.py
rpc_over_redis-0.0.5.dist-info/LICENSE
rpc_over_redis-0.0.5.dist-info/METADATA
rpc_over_redis-0.0.5.dist-info/WHEEL
rpc_over_redis-0.0.5.dist-info/top_level.txt
rpc_over_redis-0.0.5.dist-info/RECORD
